.gitignore
README.md
setup.cfg
setup.py
_skbuild/linux-x86_64-3.10/cmake-install/bin/binvox2bt
_skbuild/linux-x86_64-3.10/cmake-install/bin/bt2vrml
_skbuild/linux-x86_64-3.10/cmake-install/bin/compare_octrees
_skbuild/linux-x86_64-3.10/cmake-install/bin/convert_octree
_skbuild/linux-x86_64-3.10/cmake-install/bin/edit_octree
_skbuild/linux-x86_64-3.10/cmake-install/bin/eval_octree_accuracy
_skbuild/linux-x86_64-3.10/cmake-install/bin/graph2tree
_skbuild/linux-x86_64-3.10/cmake-install/bin/log2graph
_skbuild/linux-x86_64-3.10/cmake-install/include/dynamicEDT3D/bucketedqueue.h
_skbuild/linux-x86_64-3.10/cmake-install/include/dynamicEDT3D/bucketedqueue.hxx
_skbuild/linux-x86_64-3.10/cmake-install/include/dynamicEDT3D/dynamicEDT3D.h
_skbuild/linux-x86_64-3.10/cmake-install/include/dynamicEDT3D/dynamicEDTOctomap.h
_skbuild/linux-x86_64-3.10/cmake-install/include/dynamicEDT3D/point.h
_skbuild/linux-x86_64-3.10/cmake-install/include/octomap/AbstractOcTree.h
_skbuild/linux-x86_64-3.10/cmake-install/include/octomap/AbstractOccupancyOcTree.h
_skbuild/linux-x86_64-3.10/cmake-install/include/octomap/ColorOcTree.h
_skbuild/linux-x86_64-3.10/cmake-install/include/octomap/CountingOcTree.h
_skbuild/linux-x86_64-3.10/cmake-install/include/octomap/MCTables.h
_skbuild/linux-x86_64-3.10/cmake-install/include/octomap/MapCollection.h
_skbuild/linux-x86_64-3.10/cmake-install/include/octomap/MapCollection.hxx
_skbuild/linux-x86_64-3.10/cmake-install/include/octomap/MapNode.h
_skbuild/linux-x86_64-3.10/cmake-install/include/octomap/MapNode.hxx
_skbuild/linux-x86_64-3.10/cmake-install/include/octomap/OcTree.h
_skbuild/linux-x86_64-3.10/cmake-install/include/octomap/OcTreeBase.h
_skbuild/linux-x86_64-3.10/cmake-install/include/octomap/OcTreeBaseImpl.h
_skbuild/linux-x86_64-3.10/cmake-install/include/octomap/OcTreeBaseImpl.hxx
_skbuild/linux-x86_64-3.10/cmake-install/include/octomap/OcTreeDataNode.h
_skbuild/linux-x86_64-3.10/cmake-install/include/octomap/OcTreeDataNode.hxx
octomap_ros.egg-info/PKG-INFO
octomap_ros.egg-info/SOURCES.txt
octomap_ros.egg-info/dependency_links.txt
octomap_ros.egg-info/not-zip-safe
octomap_ros.egg-info/requires.txt
octomap_ros.egg-info/top_level.txt
