Metadata-Version: 2.1
Name: octomap_ros
Version: 1.8.2
Summary: Python binding of the OctoMap library.
Home-page: https://github.com/ethanmclark1/octomap_ros
Author: Ethan Clark, Blake Narramore
Author-email: eclark715@gmail.com, blaque2pi@msn.com
Maintainer: Ethan Clark
Maintainer-email: eclark715@gmail.com
License: BSD
Classifier: Development Status :: 5 - Production/Stable
Classifier: Intended Audience :: Developers
Classifier: Natural Language :: English
Classifier: Programming Language :: Python
Classifier: Programming Language :: Python :: 2
Classifier: Programming Language :: Python :: 3
Classifier: Programming Language :: Python :: Implementation :: CPython
Classifier: Programming Language :: Python :: Implementation :: PyPy
Requires-Dist: numpy<1.25.0,>=1.24.3
Provides-Extra: example
Requires-Dist: glooey; extra == "example"
Requires-Dist: imgviz>=1.2.0; extra == "example"
Requires-Dist: pyglet; extra == "example"
Requires-Dist: trimesh[easy]; extra == "example"
